ttsdb_core/__init__.py
ttsdb_core/config.py
ttsdb_core/vendor.py
ttsdb_core/weights.py
ttsdb_core/testing/__init__.py
ttsdb_core/testing/fixtures.py
ttsdb_core/testing/pytest_helpers.py
ttsdb_core/testing/testkit.py
ttsdb_core-0.1.4.dist-info/METADATA
ttsdb_core-0.1.4.dist-info/WHEEL
ttsdb_core-0.1.4.dist-info/RECORD
