Metadata-Version: 2.4
Name: ttsdb-core
Version: 0.1.4
Summary: Core package for TTSDB systems - base classes for voice cloning TTS models.
Requires-Python: >=3.8
Requires-Dist: importlib-resources>=5.0; python_version < '3.9'
Requires-Dist: numpy>=1.21.0
Requires-Dist: pyyaml>=6.0
Requires-Dist: scipy>=1.7.0
Requires-Dist: soundfile>=0.10.0
Requires-Dist: transformers>=4.20.0
